README.rst
setup.cfg
setup.py
wagent/AgentConnection.py
wagent/AgentException.py
wagent/WinduAgent.py
wagent/__init__.py
wagent.egg-info/PKG-INFO
wagent.egg-info/SOURCES.txt
wagent.egg-info/dependency_links.txt
wagent.egg-info/top_level.txt
wagent/php/agent-server
wagent/php/agent-server.php
wagent/php/check_file.php
wagent/php/wagent-prot.php
wagent/php/external/chatapi/LICENSE
wagent/php/external/chatapi/README.md
wagent/php/external/chatapi/composer.json
wagent/php/external/chatapi/examples/Simple CLI client.php
wagent/php/external/chatapi/examples/blockChecker.php
wagent/php/external/chatapi/examples/contactsync.php
wagent/php/external/chatapi/examples/exampleFunctional.php
wagent/php/external/chatapi/examples/exampleRegister.php
wagent/php/external/chatapi/examples/registerTool.php
wagent/php/external/chatapi/examples/resetAccount.php
wagent/php/external/chatapi/examples/whatsapp.php
wagent/php/external/chatapi/examples/WA CLI Client/client.php
wagent/php/external/chatapi/examples/ajaxDemo/ajax.php
wagent/php/external/chatapi/examples/ajaxDemo/index.php
wagent/php/external/chatapi/examples/ajaxDemo/jquery.js
wagent/php/external/chatapi/examples/ajaxDemo/socket.php
wagent/php/external/chatapi/examples/chosen/chosen-sprite.png
wagent/php/external/chatapi/examples/chosen/chosen.css
wagent/php/external/chatapi/examples/chosen/chosen.jquery.min.js
wagent/php/external/chatapi/examples/demo/venom.jpg
wagent/php/external/chatapi/examples/demo/x3.jpg
wagent/php/external/chatapi/examples/emoji/emojisprite.css
wagent/php/external/chatapi/examples/emoji/emojisprite.png
wagent/php/external/chatapi/examples/media/media_goes_here
wagent/php/external/chatapi/examples/pictures/profile_pictures_go_here
wagent/php/external/chatapi/src/BinTreeNodeReader.php
wagent/php/external/chatapi/src/BinTreeNodeWriter.php
wagent/php/external/chatapi/src/Constants.php
wagent/php/external/chatapi/src/Logger.php
wagent/php/external/chatapi/src/Login.php
wagent/php/external/chatapi/src/NewMsgBindInterface.php
wagent/php/external/chatapi/src/Registration.php
wagent/php/external/chatapi/src/SqliteAxolotlStore.php
