Metadata-Version: 1.1
Name: wagent
Version: 1.0.259
Summary: Windu message agent
Home-page: https://github.com/codefoco/wagent
Author: Vinicius Jarina
Author-email: viniciusjarina@gmail.com
License: MIT
Keywords: sample setuptools development
Platform: UNKNOWN
Classifier: Development Status :: 3 - Alpha
Classifier: Intended Audience :: Developers
Classifier: Topic :: Software Development :: Build Tools
Classifier: License :: OSI Approved :: MIT License
Classifier: Programming Language :: Python :: 2
Classifier: Programming Language :: Python :: 2.6
Classifier: Programming Language :: Python :: 2.7
Classifier: Programming Language :: Python :: 3
Classifier: Programming Language :: Python :: 3.2
Classifier: Programming Language :: Python :: 3.3
Classifier: Programming Language :: Python :: 3.4
